LICENSE
MANIFEST.in
README.rst
setup.py
tasks.py
pyspotify_connect.egg-info/PKG-INFO
pyspotify_connect.egg-info/SOURCES.txt
pyspotify_connect.egg-info/dependency_links.txt
pyspotify_connect.egg-info/not-zip-safe
pyspotify_connect.egg-info/requires.txt
pyspotify_connect.egg-info/top_level.txt
spotifyconnect/__init__.py
spotifyconnect/_spotifyconnect_build.py
spotifyconnect/_zeroconfserver.py
spotifyconnect/audio.py
spotifyconnect/config.py
spotifyconnect/connection.py
spotifyconnect/error.py
spotifyconnect/eventloop.py
spotifyconnect/metadata.py
spotifyconnect/player.py
spotifyconnect/session.py
spotifyconnect/sink.py
spotifyconnect/spotify.armv6l.h
spotifyconnect/spotify.armv7l.h
spotifyconnect/spotify.processed.armv6l.h
spotifyconnect/spotify.processed.armv7l.h
spotifyconnect/utils.py
spotifyconnect/zeroconf.py