Metadata-Version: 1.1
Name: pyspotify-connect
Version: 0.1.13
Summary: Python wrapper for libspotify-connect
Home-page: https://github.com/chukysoria/pyspotify-connect
Author: chukysoria
Author-email: nomail@nomail.com
License: Apache License, Version 2.0
Keywords: s,p,o,t,i,f,y, ,c,o,n,n,e,c,t, ,l,i,b,r,a,r,y
Platform: UNKNOWN
Classifier: Development Status :: 3 - Alpha
Classifier: Intended Audience :: Developers
Classifier: License :: OSI Approved :: Apache Software License
Classifier: Programming Language :: Python :: 2
Classifier: Programming Language :: Python :: 2.7
Classifier: Programming Language :: Python :: 3
Classifier: Programming Language :: Python :: 3.3
Classifier: Programming Language :: Python :: 3.4
Classifier: Programming Language :: Python :: Implementation :: CPython
Classifier: Programming Language :: Python :: Implementation :: PyPy
Classifier: Topic :: Software Development :: Libraries
